mesmerize/VERSION
mesmerize/__init__.py
mesmerize/__main__.py
mesmerize/analysis/__init__.py
mesmerize/analysis/batch_manager_reader.py
mesmerize/analysis/clustering_metrics.py
mesmerize/analysis/compute_peak_features.py
mesmerize/analysis/data_types.py
mesmerize/analysis/flowchart.py
mesmerize/analysis/history_widget.py
mesmerize/analysis/meta_clustering.py
mesmerize/analysis/register_sessions.py
mesmerize/analysis/sequences.py
mesmerize/analysis/simple_plot_window.py
mesmerize/analysis/stimulus_extraction.py
mesmerize/analysis/utils.py
mesmerize/analysis/math/__init__.py
mesmerize/analysis/math/cross_correlation.py
mesmerize/analysis/math/drfft_dtw.py
mesmerize/analysis/math/emd.py
mesmerize/analysis/math/sosd.py
mesmerize/analysis/math/tvregdiff.py
mesmerize/analysis/pipeline/__init__.py
mesmerize/analysis/pipeline/containers.py
mesmerize/analysis/pipeline/node_library/__init__.py
mesmerize/analysis/pipeline/node_library/cluster.py
mesmerize/analysis/pipeline/node_library/data.py
mesmerize/analysis/pipeline/node_library/signal.py
mesmerize/analysis/pipeline/node_library/stats.py
mesmerize/analysis/pytemplates/__init__.py
mesmerize/analysis/pytemplates/mainwindow_pytemplate.py
mesmerize/analysis/pytemplates/plot_window_pytemplate.py
mesmerize/analysis/pytemplates/old/PeakEditor_pytemplate.py
mesmerize/analysis/pytemplates/old/__init__.py
mesmerize/analysis/pytemplates/old/beeswarm_plots_pytemplate.py
mesmerize/analysis/pytemplates/old/pca_window_pytemplate.py
mesmerize/analysis/pytemplates/old/stats_gui_pytemplate.py
mesmerize/analysis/pytemplates/old/stats_peak_plots_pytemplate.py
mesmerize/analysis/pytemplates/old/stim_plots_pytemplate.py
mesmerize/common/__init__.py
mesmerize/common/configuration.py
mesmerize/common/help_info.py
mesmerize/common/misc_functions.py
mesmerize/common/process_utils.py
mesmerize/common/project_config_window.py
mesmerize/common/qdialogs.py
mesmerize/common/start.py
mesmerize/common/system_config_window.py
mesmerize/common/utils.py
mesmerize-0.8.0.dist-info/LICENSE
mesmerize-0.8.0.dist-info/METADATA
mesmerize-0.8.0.dist-info/WHEEL
mesmerize-0.8.0.dist-info/entry_points.txt
mesmerize-0.8.0.dist-info/top_level.txt
mesmerize-0.8.0.dist-info/RECORD
