Metadata-Version: 2.1
Name: mesmerize
Version: 0.8.0
Summary: Calcium imaging analysis platform
Home-page: https://github.com/kushalkolar/MESmerize
Author: Kushal Kolar, Daniel Dondorp
Author-email: kushalkolar@gmail.com
License: GNU General Public License v3.0
Platform: UNKNOWN
Classifier: Programming Language :: Python :: 3
Classifier: License :: OSI Approved :: GNU General Public License v3 or later (GPLv3+)
Classifier: Operating System :: POSIX :: Linux
Classifier: Operating System :: MacOS :: MacOS X
Classifier: Operating System :: Microsoft :: Windows :: Windows 10
Classifier: Topic :: Scientific/Engineering :: Bio-Informatics
Classifier: Topic :: Scientific/Engineering :: Image Recognition
Classifier: Topic :: Scientific/Engineering :: Information Analysis
Classifier: Topic :: Scientific/Engineering :: Visualization
Classifier: Intended Audience :: Science/Research
Requires-Python: >=3.6
Requires-Dist: cycler (==0.10.0)
Requires-Dist: dask (>=1.1.1)
Requires-Dist: future (>=0.18.2)
Requires-Dist: h5py (~=2.10.0)
Requires-Dist: ipykernel (>=4.10)
Requires-Dist: ipython (>=7.15.0)
Requires-Dist: ipyparallel (>=6.3)
Requires-Dist: MarkupSafe (>=1.1.1)
Requires-Dist: matplotlib (<=3.2.1)
Requires-Dist: opencv-contrib-python (>=4.2)
Requires-Dist: opencv-python (>=4.2)
Requires-Dist: pandas
Requires-Dist: Pillow (>=5.4.1)
Requires-Dist: psutil
Requires-Dist: PyQt5 (<=5.12,>=5.9.2)
Requires-Dist: python-dateutil (>=2.8.0)
Requires-Dist: QtPy (>=1.6.0)
Requires-Dist: qtap
Requires-Dist: scikit-image (~=0.15.0)
Requires-Dist: scikit-learn (~=0.23.1)
Requires-Dist: scipy (>=1.2.1)
Requires-Dist: seaborn (==0.9.0)
Requires-Dist: spyder (==3.3.3)
Requires-Dist: tifffile
Requires-Dist: tqdm (>=4.37.0)
Requires-Dist: PeakUtils
Requires-Dist: tables (>=3.6.1)
Requires-Dist: joblib (>=0.15.1)
Requires-Dist: graphviz (>=0.13)
Requires-Dist: numba (>=0.50.0)
Requires-Dist: holoviews
Requires-Dist: jupyter
Requires-Dist: pynwb
Requires-Dist: pyqtgraph
Requires-Dist: tk
Requires-Dist: tcl
Requires-Dist: bokeh (<2.5.0,>=2.4.0)
Requires-Dist: nuset-lib
Requires-Dist: sk-video
Requires-Dist: click
Requires-Dist: xmltodict
